c8y_api/__init__.py
c8y_api/_auth.py
c8y_api/_base_api.py
c8y_api/_jwt.py
c8y_api/_main_api.py
c8y_api/_registry_api.py
c8y_api/_util.py
c8y_api/app/__init__.py
c8y_api/model/__init__.py
c8y_api/model/_base.py
c8y_api/model/_parser.py
c8y_api/model/_util.py
c8y_api/model/administration.py
c8y_api/model/alarms.py
c8y_api/model/applications.py
c8y_api/model/audit.py
c8y_api/model/binaries.py
c8y_api/model/events.py
c8y_api/model/identity.py
c8y_api/model/inventory.py
c8y_api/model/managedobjects.py
c8y_api/model/measurements.py
c8y_api/model/notification2.py
c8y_api/model/operations.py
c8y_api/model/tenant_options.py
c8y_api/model/tenants.py
c8y_api/model/matcher/__init__.py
c8y_api/model/matcher/_jmespath_matcher.py
c8y_api/model/matcher/_jsonpath_matcher.py
c8y_api/model/matcher/_matcher.py
c8y_api/model/matcher/_pydf_matcher.py
c8y_tk/__init__.py
c8y_tk/analytics/__init__.py
c8y_tk/analytics/_parallel.py
c8y_tk/analytics/_wrappers.py
c8y_tk/app/__init__.py
c8y_tk/app/interactive.py
c8y_tk/app/subscription_listener.py
c8y_tk/notification2/__init__.py
c8y_tk/notification2/listener.py
c8y_api-3.6.0.dist-info/METADATA
c8y_api-3.6.0.dist-info/WHEEL
c8y_api-3.6.0.dist-info/licenses/LICENSE
c8y_api-3.6.0.dist-info/RECORD
