Metadata-Version: 2.4
Name: c8y_api
Version: 3.6.0
Summary: Python microservice and application client for the Cumulocity REST API
Project-URL: Homepage, https://github.com/Cumulocity-IoT/cumulocity-python-api
Project-URL: Source, https://github.com/Cumulocity-IoT/cumulocity-python-api
Project-URL: Issues, https://github.com/Cumulocity-IoT/cumulocity-python-api/issues
Project-URL: Documentation, https://cumulocity-python-api.readthedocs.io/en/latest/
Author-email: Christoph Souris <christoph.souris@gmail.com>
License:                                  Apache License
License-File: LICENSE
Classifier: Development Status :: 4 - Beta
Classifier: License :: OSI Approved :: Apache Software License
Classifier: Operating System :: OS Independent
Classifier: Programming Language :: Python :: 3
Classifier: Topic :: Software Development :: Libraries :: Python Modules
Requires-Python: >=3.7
Requires-Dist: cachetools
Requires-Dist: certifi
Requires-Dist: deprecated
Requires-Dist: importlib-metadata; python_version < '3.8'
Requires-Dist: inputimeout
Requires-Dist: pyjwt
Requires-Dist: python-dateutil
Requires-Dist: pyyaml
Requires-Dist: requests
Requires-Dist: websockets
Provides-Extra: filters
Requires-Dist: jmespath; extra == 'filters'
Requires-Dist: jsonpath-ng; extra == 'filters'
Requires-Dist: python-dict-display-filter; extra == 'filters'
Provides-Extra: jmespath
Requires-Dist: jmespath; extra == 'jmespath'
Provides-Extra: jsonpath
Requires-Dist: jsonpath-ng; extra == 'jsonpath'
Provides-Extra: pydf
Requires-Dist: python-dict-display-filter; extra == 'pydf'
